apep/__init__.py
apep/dictioners.py
apep/env_var.py
apep/numero.py
apep/picklejar.py
apep/tests/test_dictioners.py
apep/tests/test_numero.py
apep/tests/test_picklejar.py
elio_apep-1.0.dist-info/LICENSE
elio_apep-1.0.dist-info/METADATA
elio_apep-1.0.dist-info/WHEEL
elio_apep-1.0.dist-info/top_level.txt
elio_apep-1.0.dist-info/RECORD
