Metadata-Version: 2.1
Name: elio-apep
Version: 1.0
Summary: A collection of util functions and methods writ in python the elioWay.
Home-page: https://elioway.gitlab.io/elioangels/apep
Author: Tim Bushell
Author-email: tcbushell@gmail.com
License: UNKNOWN
Platform: UNKNOWN
Classifier: Development Status :: 3 - Alpha
Classifier: Environment :: Console
Classifier: Intended Audience :: Developers
Classifier: License :: OSI Approved :: MIT License
Classifier: Natural Language :: English
Classifier: Operating System :: OS Independent
Classifier: Programming Language :: Python
Classifier: Programming Language :: Python :: 3
Classifier: Topic :: Software Development :: Libraries
Classifier: Topic :: Utilities
